{
  "plugins": {
    "release-it-pnpm": {},
    "@release-it/conventional-changelog": {
      "preset": {
        "name": "conventionalcommits",
        "types": [
          {
            "type": "feat",
            "section": "âœ¨ æ–°åŠŸèƒ½"
          },
          {
            "type": "fix",
            "section": "ðŸ› Bug ä¿®å¤"
          },
          {
            "type": "docs",
            "section": "ðŸ“ æ–‡æ¡£"
          },
          {
            "type": "style",
            "section": "ðŸ’„ æ ·å¼"
          },
          {
            "type": "refactor",
            "section": "â™»ï¸ é‡æž„"
          },
          {
            "type": "perf",
            "section": "âš¡ æ€§èƒ½ä¼˜åŒ–"
          },
          {
            "type": "test",
            "section": "âœ… æµ‹è¯•"
          },
          {
            "type": "build",
            "section": "ðŸ“¦ æž„å»º"
          },
          {
            "type": "ci",
            "section": "ðŸ‘· CI"
          },
          {
            "type": "chore",
            "section": "ðŸ”¨ å…¶ä»–"
          },
          {
            "type": "revert",
            "section": "âª å›žé€€"
          },
          {
            "type": "wip",
            "section": "ðŸš§ è¿›è¡Œä¸­"
          },
          {
            "type": "init",
            "section": "ðŸŽ‰ åˆå§‹åŒ–"
          },
          {
            "type": "deps",
            "section": "ðŸ“Œ ä¾èµ–"
          },
          {
            "type": "i18n",
            "section": "ðŸŒ å›½é™…åŒ–"
          },
          {
            "type": "typo",
            "section": "âœï¸ æ‹¼å†™"
          },
          {
            "type": "config",
            "section": "âš™ï¸ é…ç½®"
          }
        ]
      },
      "infile": "CHANGELOG.md",
      "header": "# Changelog",
      "writerOpts": {
        "commitPartial": "* {{header}} ([{{shortHash}}](https://github.com/aatrooox/blog.zzao.club/commit/{{hash}}))\n",
        "mainTemplate": "{{> header}}\n\n{{#each commitGroups}}\n\n{{#if title}}\n### {{title}}\n\n{{/if}}\n{{#each commits}}\n{{> commit root=@root}}\n{{/each}}\n{{/each}}\n\n{{> footer}}"
      }
    }
  },
  "github": {
    "release": false,
    "tokenRef": false,
    "assets": false,
    "skipChecks": true
  },
  "git": {
    "requireCleanWorkingDir": true,
    "requireBranch": false,
    "requireUpstream": false,
    "requireCommits": true,
    "addUntrackedFiles": false,
    "commit": true,
    "commitMessage": "chore: release v${version}",
    "tag": true,
    "push": false,
    "changelog": true
  },
  "hooks": {
    "after:release": "git push origin --follow-tags"
  },
  "npm": false
}