{
  "code": "005",
  "name": "Mac Folder - Fresh Blue",
  "description": "Mac文件夹风格封面，清新蓝调，2.35:1比例，适合文章封面",
  "template": "MacFolder",
  "width": 1410,
  "height": 600,
  "contentProps": {
    "content": [[{"text": "能力强的人用", "type": "text"}, {"text": "AI", "type": "accent"}, {"text": "更强", "type": "text"}]]
  },
  "styleProps": {
    "bgColor": "#f0f8ff",
    "folderColor": "#a8d5e5",
    "folderTopColor": "#7fb3d5",
    "colors": ["#1e3a5f"],
    "accentColors": ["#3b82f6"],
    "fontSizes": ["64px"],
    "aligns": ["justify-center"],
    "fontFamily": "YouSheBiaoTiHei",
    "padding": "60px",
    "watermarkColor": "#94a3b8"
  },
  "contentKeys": "text"
}
